popyrous/__init__.py
popyrous/utils.py
popyrous/matlab/__init__.py
popyrous/matlab/matlab.py
popyrous/ml/__init__.py
popyrous/ml/confusion_matrix.py
popyrous/packages/__init__.py
popyrous/packages/packages.py
popyrous/timeseries/__init__.py
popyrous/timeseries/cwt.py
popyrous/timeseries/datasets.py
popyrous/timeseries/experiment.py
popyrous/timeseries/filt.py
popyrous/timeseries/metrics.py
popyrous/timeseries/recipe_577504_1.py
popyrous/timeseries/sliding_window.py
popyrous/web/__init__.py
popyrous/web/download.py
popyrous/zipfiles/__init__.py
popyrous/zipfiles/zipfiles.py
popyrous-0.0.13.dist-info/LICENSE.txt
popyrous-0.0.13.dist-info/METADATA
popyrous-0.0.13.dist-info/WHEEL
popyrous-0.0.13.dist-info/top_level.txt
popyrous-0.0.13.dist-info/RECORD
