Metadata-Version: 2.1
Name: popyrous
Version: 0.0.13
Summary: Pouya's Python routines. A collection of useful Python routines for everyday and professional life.
Home-page: https://github.com/pniaz20/popyrous
Author: Pouya P. Niaz
Author-email: <pniaz20@ku.edu.tr>
License: MIT
Keywords: python,routines,matlab,zipfile,packages,time series,filtering,download,web
Classifier: Development Status :: 3 - Alpha
Classifier: Intended Audience :: End Users/Desktop
Classifier: License :: OSI Approved :: MIT License
Classifier: Programming Language :: Python :: 3
Classifier: Operating System :: OS Independent
Classifier: Topic :: Utilities
Requires-Python: >=3.7, <4
License-File: LICENSE.txt
Requires-Dist: numpy
Requires-Dist: scipy
Requires-Dist: pandas
Requires-Dist: matplotlib
Requires-Dist: seaborn
Requires-Dist: scikit-learn
Requires-Dist: gdown
Requires-Dist: pywavelets
